unitprefix/__init__.py
unitprefix/unitprefix.py
unitprefix-0.1.dist-info/LICENSE
unitprefix-0.1.dist-info/METADATA
unitprefix-0.1.dist-info/WHEEL
unitprefix-0.1.dist-info/top_level.txt
unitprefix-0.1.dist-info/RECORD
